jsonschema_lexer/__init__.py
jsonschema_lexer/_lexer.py
jsonschema_lexer/py.typed
jsonschema_lexer/data/keywords/draft-03.json
jsonschema_lexer/data/keywords/draft-04.json
jsonschema_lexer/data/keywords/draft-06.json
jsonschema_lexer/data/keywords/draft-07.json
jsonschema_lexer/data/keywords/draft2019-09.json
jsonschema_lexer/data/keywords/draft2020-12.json
jsonschema_lexer/tests/__init__.py
jsonschema_lexer/tests/test_integration.py
jsonschema_lexer-0.3.0.dist-info/METADATA
jsonschema_lexer-0.3.0.dist-info/WHEEL
jsonschema_lexer-0.3.0.dist-info/licenses/COPYING
jsonschema_lexer-0.3.0.dist-info/RECORD
