Metadata-Version: 2.4
Name: jsonschema-lexer
Version: 0.3.0
Summary: A Pygments lexer for JSON Schema
Project-URL: Issues, https://github.com/python-jsonschema/jsonschema-lexer/issues/
Project-URL: Source, https://github.com/python-jsonschema/jsonschema-lexer
Author-email: Julian Berman <Julian+jsonschema-lexer@GrayVines.com>
License-Expression: MIT
License-File: COPYING
Keywords: json,jsonschema
Classifier: Development Status :: 3 - Alpha
Classifier: Intended Audience :: Developers
Classifier: Operating System :: OS Independent
Classifier: Programming Language :: Python
Classifier: Programming Language :: Python :: 3.10
Classifier: Programming Language :: Python :: 3.11
Classifier: Programming Language :: Python :: 3.12
Classifier: Programming Language :: Python :: 3.13
Classifier: Programming Language :: Python :: Implementation :: CPython
Classifier: Programming Language :: Python :: Implementation :: PyPy
Classifier: Topic :: File Formats :: JSON
Classifier: Topic :: File Formats :: JSON :: JSON Schema
Requires-Python: >=3.10
Requires-Dist: pygments>=2.17.2
